pytweets/__init__.py
pytweets-0.2.dist-info/LICENSE
pytweets-0.2.dist-info/METADATA
pytweets-0.2.dist-info/WHEEL
pytweets-0.2.dist-info/top_level.txt
pytweets-0.2.dist-info/RECORD
