Metadata-Version: 2.1
Name: pytweets
Version: 0.2
Summary: PyTweets: Simple Python Twitter API
Home-page: https://github.com/sinarezaei/pytweets
Author: Sina Rezaei
Author-email: sinarezaei1991@gmail.com
License: MIT
Platform: UNKNOWN
Classifier: Programming Language :: Python :: 3
Classifier: License :: OSI Approved :: MIT License
Classifier: Operating System :: OS Independent
Requires-Python: >=3.4
